.bumpversion.cfg
.dockerignore
.gitignore
CHANGELOG.md
Dockerfile
MANIFEST.in
README.md
completer.hist
justfile
requirements-dev.txt
requirements-flake8.txt
requirements.txt
setup.py
template-version.txt
tox.ini
.githooks/prepare-commit-msg
.vscode/settings.json
Examples/README.md
Examples/tasks_example.yml
src/fhs_xmltv_tools/__init__.py
src/fhs_xmltv_tools/__version__.py
src/fhs_xmltv_tools/cli.py
src/fhs_xmltv_tools/config.py
src/fhs_xmltv_tools/fhs_xmltv_tools.py
src/fhs_xmltv_tools/func_xmltv.py
src/fhs_xmltv_tools/interactive_cmd2.py
src/fhs_xmltv_tools/playyaml.py
src/fhs_xmltv_tools/playyaml_funcs.py
src/fhs_xmltv_tools/playyaml_lib.py
src/fhs_xmltv_tools/sql.py
src/fhs_xmltv_tools/xmltv2sql.py
src/fhs_xmltv_tools/xmltv_channels.py
src/fhs_xmltv_tools/xmltv_load_save.py
src/fhs_xmltv_tools/xmltv_programs.py
src/fhs_xmltv_tools.egg-info/PKG-INFO
src/fhs_xmltv_tools.egg-info/SOURCES.txt
src/fhs_xmltv_tools.egg-info/dependency_links.txt
src/fhs_xmltv_tools.egg-info/entry_points.txt
src/fhs_xmltv_tools.egg-info/requires.txt
src/fhs_xmltv_tools.egg-info/top_level.txt
tests/test_sample.py