Metadata-Version: 2.1
Name: fhs-xmltv-tools
Version: 0.1.16
Summary: xmltv tools
Home-page: https://github.com/foxhunt72/fhs-xmltv-tools
Author: Richard de Vos
Author-email: rdevos72@gmail.com
License: MIT license
Classifier: Development Status :: 4 - Beta
Classifier: Programming Language :: Python
Classifier: Programming Language :: Python :: 3
Classifier: Programming Language :: Python :: 3.7
Classifier: Programming Language :: Python :: 3.8
Classifier: Programming Language :: Python :: 3.9
Classifier: Programming Language :: Python :: 3.10
Requires-Dist: py-xmltv
Requires-Dist: typer[all]
Requires-Dist: pyyaml
Requires-Dist: cmd2
Requires-Dist: jinja2
Provides-Extra: sqlite
Requires-Dist: sqlalchemy; extra == "sqlite"
Provides-Extra: all
Requires-Dist: sqlalchemy; extra == "all"
